rinoh_typeface_texgyrechorus/GUST-FONT-LICENSE.txt
rinoh_typeface_texgyrechorus/README-TeX-Gyre-Chorus.txt
rinoh_typeface_texgyrechorus/__init__.py
rinoh_typeface_texgyrechorus/texgyrechorus-mediumitalic.otf
rinoh_typeface_texgyrechorus-0.1.1.dist-info/DESCRIPTION.rst
rinoh_typeface_texgyrechorus-0.1.1.dist-info/METADATA
rinoh_typeface_texgyrechorus-0.1.1.dist-info/RECORD
rinoh_typeface_texgyrechorus-0.1.1.dist-info/WHEEL
rinoh_typeface_texgyrechorus-0.1.1.dist-info/entry_points.txt
rinoh_typeface_texgyrechorus-0.1.1.dist-info/metadata.json
rinoh_typeface_texgyrechorus-0.1.1.dist-info/top_level.txt
